[
  {
    "url": "https://www.niddk.nih.gov/health-information/digestive-diseases/irritable-bowel-syndrome",
    "title": "Irritable Bowel Syndrome (IBS) | NIDDK",
    "category": "Overview"
  },
  {
    "url": "https://www.ncbi.nlm.nih.gov/pmc/articles/PMC7386065/",
    "title": "Small Intestinal Bacterial Overgrowth: A Comprehensive Review",
    "category": "Research"
  },
  {
    "url": "https://www.ncbi.nlm.nih.gov/pmc/articles/PMC5347643/",
    "title": "Hydrogen and Methane-Based Breath Testing in Gastrointestinal Disorders",
    "category": "Testing"
  },
  {
    "url": "https://pmc.ncbi.nlm.nih.gov/articles/PMC10132719/",
    "title": "Understanding Our Tests: Hydrogen-Methane Breath Testing to Diagnose Small Intestinal Bacterial Overgrowth",
    "category": "Testing"
  },
  {
    "url": "https://pmc.ncbi.nlm.nih.gov/articles/PMC3099351/",
    "title": "Small Intestinal Bacterial Overgrowth: A Comprehensive Review",
    "category": "Research"
  },
   {
    "url": "https://www.niddk.nih.gov/health-information/digestive-diseases/chronic-diarrhea-children/all-content",
    "title": "Chronic diarrhea in children",
    "category": "Overview"
  }
]
